rcore/__init__.py
rcore/__main__.py
rcore/analyze.py
rcore/cli.py
rcore/cliengine.py
rcore/config.py
rcore/entrypoint.py
rcore/exception/__init__.py
rcore/exception/errors.py
rcore/exception/exception.py
rcore/exception/info.py
rcore/exception/traceback.py
rcore/localization.py
rcore/main.py
rcore/readme.md
rcore/rpath.py
rcore/rtype.py
rcore/strpython.py
rcore/sync/__init__.py
rcore/sync/controllers/__init__.py
rcore/sync/controllers/managers.py
rcore/sync/controllers/workers.py
rcore/sync/process.py
rcore/sync/thread.py
rcore/utils.py
rcore/venv/__init__.py
rcore-0.1.14.dist-info/LICENSE
rcore-0.1.14.dist-info/WHEEL
rcore-0.1.14.dist-info/METADATA
rcore-0.1.14.dist-info/RECORD
